{"resource": "playercareerstats", "resultSets": [{"headers": ["PLAYER_ID", "SEASON_ID", "LEAGUE_ID", "TEAM_ID", "TEAM_ABBREVIATION", "PLAYER_AGE", "GP", "GS", "MIN", "FGM", "FGA", "FG_PCT", "FG3M", "FG3A", "FG3_PCT", "FTM", "FTA", "FT_PCT", "OREB", "DREB", "REB", "AST", "STL", "BLK", "TOV", "PF", "PTS"], "rowSet": [[78447, "1949-50", "00", 1610610030, "INO", 23.0, 31, null, 0, 82, 210, 0.39, null, null, null, 52, 88, 0.591, null, null, 0, 46, null, null, null, 84, 216], [78447, "1949-50", "00", 1610612747, "MNL", 23.0, 22, null, 0, 32, 80, 0.4, null, null, null, 11, 21, 0.524, null, null, 0, 10, null, null, null, 39, 75], [78447, "1949-50", "00", 0, "TOT", 23.0, 53, null, null, 114, 290, 0.393, null, null, null, 63, 109, 0.578, null, null, null, 56, null, null, null, 123, 291], [78447, "1950-51", "00", 1610610030, "INO", 24.0, 63, null, null, 213, 634, 0.336, null, null, null, 145, 209, 0.694, null, null, 226, 225, null, null, null, 201, 571], [78447, "1951-52", "00", 1610610030, "INO", 25.0, 55, null, 1903, 220, 549, 0.401, null, null, null, 231, 308, 0.75, null, null, 246, 137, null, null, null, 171, 671], [78447, "1952-53", "00", 1610610030, "INO", 26.0, 67, null, 2468, 227, 645, 0.352, null, null, null, 264, 354, 0.746, null, null, 284, 205, null, null, null, 260, 718], [78447, "1953-54", "00", 1610612744, "PHW", 27.0, 64, null, 2067, 138, 392, 0.352, null, null, null, 145, 206, 0.704, null, null, 257, 220, null, null, null, 199, 421], [78447, "1954-55", "00", 1610612765, "FTW", 28.0, 68, null, 820, 56, 161, 0.348, null, null, null, 54, 88, 0.614, null, null, 155, 131, null, null, null, 115, 166]], "name": "SeasonTotalsRegularSeason"}, {"headers": ["PLAYER_ID", "LEAGUE_ID", "TEAM_ID", "GP", "GS", "MIN", "FGM", "FGA", "FG_PCT", "FG3M", "FG3A", "FG3_PCT", "FTM", "FTA", "FT_PCT", "OREB", "DREB", "REB", "AST", "STL", "BLK", "TOV", "PF", "PTS"], "rowSet": [[78447, "00", 0, 370, null, 7258, 968, 2671, 0.362, null, null, null, 902, 1274, 0.708, null, null, 1168, 974, null, null, null, 1069, 2838]], "name": "CareerTotalsRegularSeason"}, {"headers": ["PLAYER_ID", "SEASON_ID", "LEAGUE_ID", "TEAM_ID", "TEAM_ABBREVIATION", "PLAYER_AGE", "GP", "GS", "MIN", "FGM", "FGA", "FG_PCT", "FG3M", "FG3A", "FG3_PCT", "FTM", "FTA", "FT_PCT", "OREB", "DREB", "REB", "AST", "STL", "BLK", "TOV", "PF", "PTS"], "rowSet": [[78447, "1949-50", "00", 1610610030, "INO", 23.0, 6, null, null, 12, 0, null, null, null, null, 8, 18, 0.444, null, null, null, 0, null, null, null, 18, 32], [78447, "1950-51", "00", 1610610030, "INO", 24.0, 3, null, null, 3, 7, 0.429, null, null, null, 11, 15, 0.733, null, null, 5, 9, null, null, null, 6, 17], [78447, "1951-52", "00", 1610610030, "INO", 25.0, 2, null, 85, 8, 16, 0.5, null, null, null, 16, 18, 0.889, null, null, 7, 6, null, null, null, 8, 32], [78447, "1952-53", "00", 1610610030, "INO", 26.0, 2, null, 75, 5, 20, 0.25, null, null, null, 16, 17, 0.941, null, null, 8, 4, null, null, null, 8, 26], [78447, "1954-55", "00", 1610612765, "FTW", 28.0, 10, null, 95, 12, 22, 0.545, null, null, null, 11, 18, 0.611, null, null, 20, 8, null, null, null, 20, 35]], "name": "SeasonTotalsPostSeason"}, {"headers": ["PLAYER_ID", "LEAGUE_ID", "TEAM_ID", "GP", "GS", "MIN", "FGM", "FGA", "FG_PCT", "FG3M", "FG3A", "FG3_PCT", "FTM", "FTA", "FT_PCT", "OREB", "DREB", "REB", "AST", "STL", "BLK", "TOV", "PF", "PTS"], "rowSet": [[78447, "00", 0, 23, null, 255, 40, 65, 0.615, null, null, null, 62, 86, 0.721, null, null, 40, 27, null, null, null, 60, 142]], "name": "CareerTotalsPostSeason"}, {"headers": ["PLAYER_ID", "SEASON_ID", "LEAGUE_ID", "TEAM_ID", "TEAM_ABBREVIATION", "PLAYER_AGE", "GP", "GS", "MIN", "FGM", "FGA", "FG_PCT", "FG3M", "FG3A", "FG3_PCT", "FTM", "FTA", "FT_PCT", "OREB", "DREB", "REB", "AST", "STL", "BLK", "TOV", "PF", "PTS"], "rowSet": [[78447, "1951-52", "00", 1610616834, "WST", 25.0, 1, null, 17, 1, 4, 0.25, null, null, null, 0, 0, null, null, null, 2, 2, null, null, null, 1, 2]], "name": "SeasonTotalsAllStarSeason"}, {"headers": ["PLAYER_ID", "LEAGUE_ID", "TEAM_ID", "GP", "GS", "MIN", "FGM", "FGA", "FG_PCT", "FG3M", "FG3A", "FG3_PCT", "FTM", "FTA", "FT_PCT", "OREB", "DREB", "REB", "AST", "STL", "BLK", "TOV", "PF", "PTS"], "rowSet": [[78447, "00", 0, 1, null, 17, 1, 4, 0.25, null, null, null, 0, 0, 0.0, null, null, 2, 2, null, null, null, 1, 2]], "name": "CareerTotalsAllStarSeason"}, {"headers": ["PLAYER_ID", "SEASON_ID", "LEAGUE_ID", "ORGANIZATION_ID", "SCHOOL_NAME", "PLAYER_AGE", "GP", "GS", "MIN", "FGM", "FGA", "FG_PCT", "FG3M", "FG3A", "FG3_PCT", "FTM", "FTA", "FT_PCT", "OREB", "DREB", "REB", "AST", "STL", "BLK", "TOV", "PF", "PTS"], "rowSet": [], "name": "SeasonTotalsCollegeSeason"}, {"headers": ["PLAYER_ID", "LEAGUE_ID", "ORGANIZATION_ID", "GP", "GS", "MIN", "FGM", "FGA", "FG_PCT", "FG3M", "FG3A", "FG3_PCT", "FTM", "FTA", "FT_PCT", "OREB", "DREB", "REB", "AST", "STL", "BLK", "TOV", "PF", "PTS"], "rowSet": [], "name": "CareerTotalsCollegeSeason"}, {"headers": ["PLAYER_ID", "SEASON_ID", "LEAGUE_ID", "TEAM_ID", "TEAM_ABBREVIATION", "PLAYER_AGE", "GP", "GS", "RANK_MIN", "RANK_FGM", "RANK_FGA", "RANK_FG_PCT", "RANK_FG3M", "RANK_FG3A", "RANK_FG3_PCT", "RANK_FTM", "RANK_FTA", "RANK_FT_PCT", "RANK_OREB", "RANK_DREB", "RANK_REB", "RANK_AST", "RANK_STL", "RANK_BLK", "RANK_TOV", "RANK_PTS", "RANK_EFF"], "rowSet": [[78447, "1950-51", "00", 1610610030, "INO", "NR", "NR", "NR", null, 38, 36, null, null, null, null, 45, 46, 54, null, null, 59, 13, null, null, null, 39, 24], [78447, "1951-52", "00", 1610610030, "INO", "NR", "NR", "NR", 39, 37, 42, null, null, null, null, 25, 26, 34, null, null, 51, 45, null, null, null, 28, 1], [78447, "1952-53", "00", 1610610030, "INO", "NR", "NR", "NR", 18, 40, 32, null, null, null, null, 19, 20, 26, null, null, 42, 23, null, null, null, 36, 1], [78447, "1953-54", "00", 1610612744, "PHW", "NR", "NR", "NR", 33, 65, 65, null, null, null, null, 43, 45, 40, null, null, 49, 16, null, null, null, 59, 1], [78447, "1954-55", "00", 1610612765, "FTW", "NR", "NR", "NR", 69, 75, 75, null, null, null, null, 70, 68, null, null, null, 67, 43, null, null, null, 74, 1]], "name": "SeasonRankingsRegularSeason"}, {"headers": ["PLAYER_ID", "SEASON_ID", "LEAGUE_ID", "TEAM_ID", "TEAM_ABBREVIATION", "PLAYER_AGE", "GP", "GS", "RANK_MIN", "RANK_FGM", "RANK_FGA", "RANK_FG_PCT", "RANK_FG3M", "RANK_FG3A", "RANK_FG3_PCT", "RANK_FTM", "RANK_FTA", "RANK_FT_PCT", "RANK_OREB", "RANK_DREB", "RANK_REB", "RANK_AST", "RANK_STL", "RANK_BLK", "RANK_TOV", "RANK_PTS", "RANK_EFF"], "rowSet": [[78447, "1951-52", "00", 1610610030, "INO", "NR", "NR", "NR", 42, 42, 54, 6, null, null, null, 30, 34, 9, null, null, 57, 44, null, null, null, 37, 1], [78447, "1952-53", "00", 1610610030, "INO", "NR", "NR", "NR", 45, 50, 45, null, null, null, null, 29, 35, 3, null, null, 48, 51, null, null, null, 39, 1], [78447, "1954-55", "00", 1610612765, "FTW", "NR", "NR", "NR", 39, 40, 46, null, null, null, null, 40, 38, null, null, null, 37, 38, null, null, null, 40, 1]], "name": "SeasonRankingsPostSeason"}], "parameters": {"PlayerID": 78447, "LeagueID": null, "PerMode": "Totals"}}