{"resource": "playercareerstats", "resultSets": [{"headers": ["PLAYER_ID", "SEASON_ID", "LEAGUE_ID", "TEAM_ID", "TEAM_ABBREVIATION", "PLAYER_AGE", "GP", "GS", "MIN", "FGM", "FGA", "FG_PCT", "FG3M", "FG3A", "FG3_PCT", "FTM", "FTA", "FT_PCT", "OREB", "DREB", "REB", "AST", "STL", "BLK", "TOV", "PF", "PTS"], "rowSet": [[78297, "1989-90", "00", 1610612751, "NJN", 22.0, 17, 0, 114, 21, 52, 0.404, 3, 13, 0.231, 6, 9, 0.667, 5, 6, 11, 5, 5, 3, 10, 9, 51]], "name": "SeasonTotalsRegularSeason"}, {"headers": ["PLAYER_ID", "LEAGUE_ID", "TEAM_ID", "GP", "GS", "MIN", "FGM", "FGA", "FG_PCT", "FG3M", "FG3A", "FG3_PCT", "FTM", "FTA", "FT_PCT", "OREB", "DREB", "REB", "AST", "STL", "BLK", "TOV", "PF", "PTS"], "rowSet": [[78297, "00", 0, 17, 0, 114, 21, 52, 0.404, 3, 13, 0.231, 6, 9, 0.667, 5, 6, 11, 5, 5, 3, 10, 9, 51]], "name": "CareerTotalsRegularSeason"}, {"headers": ["PLAYER_ID", "SEASON_ID", "LEAGUE_ID", "TEAM_ID", "TEAM_ABBREVIATION", "PLAYER_AGE", "GP", "GS", "MIN", "FGM", "FGA", "FG_PCT", "FG3M", "FG3A", "FG3_PCT", "FTM", "FTA", "FT_PCT", "OREB", "DREB", "REB", "AST", "STL", "BLK", "TOV", "PF", "PTS"], "rowSet": [], "name": "SeasonTotalsPostSeason"}, {"headers": ["PLAYER_ID", "LEAGUE_ID", "TEAM_ID", "GP", "GS", "MIN", "FGM", "FGA", "FG_PCT", "FG3M", "FG3A", "FG3_PCT", "FTM", "FTA", "FT_PCT", "OREB", "DREB", "REB", "AST", "STL", "BLK", "TOV", "PF", "PTS"], "rowSet": [], "name": "CareerTotalsPostSeason"}, {"headers": ["PLAYER_ID", "SEASON_ID", "LEAGUE_ID", "TEAM_ID", "TEAM_ABBREVIATION", "PLAYER_AGE", "GP", "GS", "MIN", "FGM", "FGA", "FG_PCT", "FG3M", "FG3A", "FG3_PCT", "FTM", "FTA", "FT_PCT", "OREB", "DREB", "REB", "AST", "STL", "BLK", "TOV", "PF", "PTS"], "rowSet": [], "name": "SeasonTotalsAllStarSeason"}, {"headers": ["PLAYER_ID", "LEAGUE_ID", "TEAM_ID", "GP", "GS", "MIN", "FGM", "FGA", "FG_PCT", "FG3M", "FG3A", "FG3_PCT", "FTM", "FTA", "FT_PCT", "OREB", "DREB", "REB", "AST", "STL", "BLK", "TOV", "PF", "PTS"], "rowSet": [], "name": "CareerTotalsAllStarSeason"}, {"headers": ["PLAYER_ID", "SEASON_ID", "LEAGUE_ID", "ORGANIZATION_ID", "SCHOOL_NAME", "PLAYER_AGE", "GP", "GS", "MIN", "FGM", "FGA", "FG_PCT", "FG3M", "FG3A", "FG3_PCT", "FTM", "FTA", "FT_PCT", "OREB", "DREB", "REB", "AST", "STL", "BLK", "TOV", "PF", "PTS"], "rowSet": [], "name": "SeasonTotalsCollegeSeason"}, {"headers": ["PLAYER_ID", "LEAGUE_ID", "ORGANIZATION_ID", "GP", "GS", "MIN", "FGM", "FGA", "FG_PCT", "FG3M", "FG3A", "FG3_PCT", "FTM", "FTA", "FT_PCT", "OREB", "DREB", "REB", "AST", "STL", "BLK", "TOV", "PF", "PTS"], "rowSet": [], "name": "CareerTotalsCollegeSeason"}, {"headers": ["PLAYER_ID", "SEASON_ID", "LEAGUE_ID", "TEAM_ID", "TEAM_ABBREVIATION", "PLAYER_AGE", "GP", "GS", "RANK_MIN", "RANK_FGM", "RANK_FGA", "RANK_FG_PCT", "RANK_FG3M", "RANK_FG3A", "RANK_FG3_PCT", "RANK_FTM", "RANK_FTA", "RANK_FT_PCT", "RANK_OREB", "RANK_DREB", "RANK_REB", "RANK_AST", "RANK_STL", "RANK_BLK", "RANK_TOV", "RANK_PTS", "RANK_EFF"], "rowSet": [[78297, "1989-90", "00", 1610612751, "NJN", "NR", "NR", "NR", 336, 323, 327, null, 150, 170, null, 343, 342, null, 342, 351, 352, 343, 321, 288, 331, 327, 342]], "name": "SeasonRankingsRegularSeason"}, {"headers": ["PLAYER_ID", "SEASON_ID", "LEAGUE_ID", "TEAM_ID", "TEAM_ABBREVIATION", "PLAYER_AGE", "GP", "GS", "RANK_MIN", "RANK_FGM", "RANK_FGA", "RANK_FG_PCT", "RANK_FG3M", "RANK_FG3A", "RANK_FG3_PCT", "RANK_FTM", "RANK_FTA", "RANK_FT_PCT", "RANK_OREB", "RANK_DREB", "RANK_REB", "RANK_AST", "RANK_STL", "RANK_BLK", "RANK_TOV", "RANK_PTS", "RANK_EFF"], "rowSet": [], "name": "SeasonRankingsPostSeason"}], "parameters": {"PlayerID": 78297, "LeagueID": null, "PerMode": "Totals"}}