{"resource": "playercareerstats", "resultSets": [{"headers": ["PLAYER_ID", "SEASON_ID", "LEAGUE_ID", "TEAM_ID", "TEAM_ABBREVIATION", "PLAYER_AGE", "GP", "GS", "MIN", "FGM", "FGA", "FG_PCT", "FG3M", "FG3A", "FG3_PCT", "FTM", "FTA", "FT_PCT", "OREB", "DREB", "REB", "AST", "STL", "BLK", "TOV", "PF", "PTS"], "rowSet": [[204037, "2014-15", "00", 1610612752, "NYK", 24.0, 51, 1, 672, 84, 209, 0.402, 11, 30, 0.367, 20, 26, 0.769, 31, 75, 106, 40, 15, 11, 35, 55, 199]], "name": "SeasonTotalsRegularSeason"}, {"headers": ["PLAYER_ID", "LEAGUE_ID", "TEAM_ID", "GP", "GS", "MIN", "FGM", "FGA", "FG_PCT", "FG3M", "FG3A", "FG3_PCT", "FTM", "FTA", "FT_PCT", "OREB", "DREB", "REB", "AST", "STL", "BLK", "TOV", "PF", "PTS"], "rowSet": [[204037, "00", 0, 51, 1, 672, 84, 209, 0.402, 11, 30, 0.367, 20, 26, 0.769, 31, 75, 106, 40, 15, 11, 35, 55, 199]], "name": "CareerTotalsRegularSeason"}, {"headers": ["PLAYER_ID", "SEASON_ID", "LEAGUE_ID", "TEAM_ID", "TEAM_ABBREVIATION", "PLAYER_AGE", "GP", "GS", "MIN", "FGM", "FGA", "FG_PCT", "FG3M", "FG3A", "FG3_PCT", "FTM", "FTA", "FT_PCT", "OREB", "DREB", "REB", "AST", "STL", "BLK", "TOV", "PF", "PTS"], "rowSet": [], "name": "SeasonTotalsPostSeason"}, {"headers": ["PLAYER_ID", "LEAGUE_ID", "TEAM_ID", "GP", "GS", "MIN", "FGM", "FGA", "FG_PCT", "FG3M", "FG3A", "FG3_PCT", "FTM", "FTA", "FT_PCT", "OREB", "DREB", "REB", "AST", "STL", "BLK", "TOV", "PF", "PTS"], "rowSet": [], "name": "CareerTotalsPostSeason"}, {"headers": ["PLAYER_ID", "SEASON_ID", "LEAGUE_ID", "TEAM_ID", "TEAM_ABBREVIATION", "PLAYER_AGE", "GP", "GS", "MIN", "FGM", "FGA", "FG_PCT", "FG3M", "FG3A", "FG3_PCT", "FTM", "FTA", "FT_PCT", "OREB", "DREB", "REB", "AST", "STL", "BLK", "TOV", "PF", "PTS"], "rowSet": [], "name": "SeasonTotalsAllStarSeason"}, {"headers": ["PLAYER_ID", "LEAGUE_ID", "TEAM_ID", "GP", "GS", "MIN", "FGM", "FGA", "FG_PCT", "FG3M", "FG3A", "FG3_PCT", "FTM", "FTA", "FT_PCT", "OREB", "DREB", "REB", "AST", "STL", "BLK", "TOV", "PF", "PTS"], "rowSet": [], "name": "CareerTotalsAllStarSeason"}, {"headers": ["PLAYER_ID", "SEASON_ID", "LEAGUE_ID", "ORGANIZATION_ID", "SCHOOL_NAME", "PLAYER_AGE", "GP", "GS", "MIN", "FGM", "FGA", "FG_PCT", "FG3M", "FG3A", "FG3_PCT", "FTM", "FTA", "FT_PCT", "OREB", "DREB", "REB", "AST", "STL", "BLK", "TOV", "PF", "PTS"], "rowSet": [[204037, "2013-14", "00", 2535, "California-Los Angeles", 23.0, 34, 28, 812, 105, 198, 0.53, 11, 25, 0.44, 25, 30, 0.833, 33, 75, 108, 49, 25, 23, 13, 104, 246], [204037, "2012-13", "00", 2535, "California-Los Angeles", 22.0, 32, 31, 924, 140, 284, 0.493, 4, 13, 0.308, 66, 81, 0.815, 51, 116, 167, 17, 23, 33, 44, 85, 350], [204037, "2011-12", "00", 2535, "California-Los Angeles", 21.0, 30, 24, 786, 137, 257, 0.533, 3, 7, 0.429, 68, 86, 0.791, 86, 92, 178, 13, 21, 36, 34, 73, 345], [204037, "2009-10", "00", 3104, "North Carolina", 19.0, 32, 1, 324, 43, 104, 0.413, 2, 6, 0.333, 23, 31, 0.742, 36, 33, 69, 7, 8, 2, 24, 35, 111]], "name": "SeasonTotalsCollegeSeason"}, {"headers": ["PLAYER_ID", "LEAGUE_ID", "ORGANIZATION_ID", "GP", "GS", "MIN", "FGM", "FGA", "FG_PCT", "FG3M", "FG3A", "FG3_PCT", "FTM", "FTA", "FT_PCT", "OREB", "DREB", "REB", "AST", "STL", "BLK", "TOV", "PF", "PTS"], "rowSet": [[204037, "00", 0, 128, 84, 2846, 425, 843, 0.504, 20, 51, 0.392, 182, 228, 0.798, 206, 316, 522, 86, 77, 94, 115, 297, 1052]], "name": "CareerTotalsCollegeSeason"}, {"headers": ["PLAYER_ID", "SEASON_ID", "LEAGUE_ID", "TEAM_ID", "TEAM_ABBREVIATION", "PLAYER_AGE", "GP", "GS", "RANK_MIN", "RANK_FGM", "RANK_FGA", "RANK_FG_PCT", "RANK_FG3M", "RANK_FG3A", "RANK_FG3_PCT", "RANK_FTM", "RANK_FTA", "RANK_FT_PCT", "RANK_OREB", "RANK_DREB", "RANK_REB", "RANK_AST", "RANK_STL", "RANK_BLK", "RANK_TOV", "RANK_PTS", "RANK_EFF"], "rowSet": [[204037, "2014-15", "00", 1610612752, "NYK", "NR", "NR", "NR", 336, 329, 323, null, 274, 291, null, 362, 368, null, 246, 332, 321, 324, 353, 270, 318, 341, 351]], "name": "SeasonRankingsRegularSeason"}, {"headers": ["PLAYER_ID", "SEASON_ID", "LEAGUE_ID", "TEAM_ID", "TEAM_ABBREVIATION", "PLAYER_AGE", "GP", "GS", "RANK_MIN", "RANK_FGM", "RANK_FGA", "RANK_FG_PCT", "RANK_FG3M", "RANK_FG3A", "RANK_FG3_PCT", "RANK_FTM", "RANK_FTA", "RANK_FT_PCT", "RANK_OREB", "RANK_DREB", "RANK_REB", "RANK_AST", "RANK_STL", "RANK_BLK", "RANK_TOV", "RANK_PTS", "RANK_EFF"], "rowSet": [], "name": "SeasonRankingsPostSeason"}], "parameters": {"PlayerID": 204037, "LeagueID": null, "PerMode": "Totals"}}