{"resource": "playercareerstats", "resultSets": [{"headers": ["PLAYER_ID", "SEASON_ID", "LEAGUE_ID", "TEAM_ID", "TEAM_ABBREVIATION", "PLAYER_AGE", "GP", "GS", "MIN", "FGM", "FGA", "FG_PCT", "FG3M", "FG3A", "FG3_PCT", "FTM", "FTA", "FT_PCT", "OREB", "DREB", "REB", "AST", "STL", "BLK", "TOV", "PF", "PTS"], "rowSet": [[203076, "2012-13", "00", 1610612740, "NOH", 20.0, 64, 60, 1846, 349, 676, 0.516, 0, 6, 0.0, 169, 225, 0.751, 165, 357, 522, 63, 75, 112, 89, 158, 867], [203076, "2013-14", "00", 1610612740, "NOP", 21.0, 67, 66, 2358, 522, 1005, 0.519, 2, 9, 0.222, 348, 440, 0.791, 207, 466, 673, 105, 89, 189, 109, 200, 1394], [203076, "2014-15", "00", 1610612740, "NOP", 22.0, 68, 68, 2455, 642, 1199, 0.535, 1, 12, 0.083, 371, 461, 0.805, 173, 523, 696, 149, 100, 200, 95, 141, 1656], [203076, "2015-16", "00", 1610612740, "NOP", 22.0, 34, 34, 1211, 294, 604, 0.487, 16, 58, 0.276, 172, 227, 0.758, 70, 291, 361, 59, 43, 83, 74, 80, 776]], "name": "SeasonTotalsRegularSeason"}, {"headers": ["PLAYER_ID", "LEAGUE_ID", "TEAM_ID", "GP", "GS", "MIN", "FGM", "FGA", "FG_PCT", "FG3M", "FG3A", "FG3_PCT", "FTM", "FTA", "FT_PCT", "OREB", "DREB", "REB", "AST", "STL", "BLK", "TOV", "PF", "PTS"], "rowSet": [[203076, "00", 0, 233, 228, 7870, 1807, 3484, 0.519, 19, 85, 0.224, 1060, 1353, 0.783, 615, 1637, 2252, 376, 307, 584, 367, 579, 4693]], "name": "CareerTotalsRegularSeason"}, {"headers": ["PLAYER_ID", "SEASON_ID", "LEAGUE_ID", "TEAM_ID", "TEAM_ABBREVIATION", "PLAYER_AGE", "GP", "GS", "MIN", "FGM", "FGA", "FG_PCT", "FG3M", "FG3A", "FG3_PCT", "FTM", "FTA", "FT_PCT", "OREB", "DREB", "REB", "AST", "STL", "BLK", "TOV", "PF", "PTS"], "rowSet": [[203076, "2014-15", "00", 1610612740, "NOP", 22.0, 4, 4, 172, 47, 87, 0.54, 0, 2, 0.0, 32, 36, 0.889, 9, 35, 44, 8, 5, 12, 13, 12, 126]], "name": "SeasonTotalsPostSeason"}, {"headers": ["PLAYER_ID", "LEAGUE_ID", "TEAM_ID", "GP", "GS", "MIN", "FGM", "FGA", "FG_PCT", "FG3M", "FG3A", "FG3_PCT", "FTM", "FTA", "FT_PCT", "OREB", "DREB", "REB", "AST", "STL", "BLK", "TOV", "PF", "PTS"], "rowSet": [[203076, "00", 0, 4, 4, 172, 47, 87, 0.54, 0, 2, 0.0, 32, 36, 0.889, 9, 35, 44, 8, 5, 12, 13, 12, 126]], "name": "CareerTotalsPostSeason"}, {"headers": ["PLAYER_ID", "SEASON_ID", "LEAGUE_ID", "TEAM_ID", "TEAM_ABBREVIATION", "PLAYER_AGE", "GP", "GS", "MIN", "FGM", "FGA", "FG_PCT", "FG3M", "FG3A", "FG3_PCT", "FTM", "FTA", "FT_PCT", "OREB", "DREB", "REB", "AST", "STL", "BLK", "TOV", "PF", "PTS"], "rowSet": [[203076, "2013-14", "00", 1610616834, "WST", 21.0, 1, 0, 10, 5, 6, 0.833, 0, 0, 0.0, 0, 0, 0.0, 0, 1, 1, 0, 2, 0, 1, 0, 10]], "name": "SeasonTotalsAllStarSeason"}, {"headers": ["PLAYER_ID", "LEAGUE_ID", "TEAM_ID", "GP", "GS", "MIN", "FGM", "FGA", "FG_PCT", "FG3M", "FG3A", "FG3_PCT", "FTM", "FTA", "FT_PCT", "OREB", "DREB", "REB", "AST", "STL", "BLK", "TOV", "PF", "PTS"], "rowSet": [[203076, "00", 0, 1, 0, 10, 5, 6, 0.833, 0, 0, 0.0, 0, 0, 0.0, 0, 1, 1, 0, 2, 0, 1, 0, 10]], "name": "CareerTotalsAllStarSeason"}, {"headers": ["PLAYER_ID", "SEASON_ID", "LEAGUE_ID", "ORGANIZATION_ID", "SCHOOL_NAME", "PLAYER_AGE", "GP", "GS", "MIN", "FGM", "FGA", "FG_PCT", "FG3M", "FG3A", "FG3_PCT", "FTM", "FTA", "FT_PCT", "OREB", "DREB", "REB", "AST", "STL", "BLK", "TOV", "PF", "PTS"], "rowSet": [[203076, "2011-12", "00", 2852, "Kentucky", 19.0, 40, 40, 1281, 210, 337, 0.623, 3, 20, 0.15, 144, 203, 0.709, 119, 296, 415, 50, 54, 186, 41, 78, 567]], "name": "SeasonTotalsCollegeSeason"}, {"headers": ["PLAYER_ID", "LEAGUE_ID", "ORGANIZATION_ID", "GP", "GS", "MIN", "FGM", "FGA", "FG_PCT", "FG3M", "FG3A", "FG3_PCT", "FTM", "FTA", "FT_PCT", "OREB", "DREB", "REB", "AST", "STL", "BLK", "TOV", "PF", "PTS"], "rowSet": [[203076, "00", 0, 40, 40, 1281, 210, 337, 0.623, 3, 20, 0.15, 144, 203, 0.709, 119, 296, 415, 50, 54, 186, 41, 78, 567]], "name": "CareerTotalsCollegeSeason"}, {"headers": ["PLAYER_ID", "SEASON_ID", "LEAGUE_ID", "TEAM_ID", "TEAM_ABBREVIATION", "PLAYER_AGE", "GP", "GS", "RANK_MIN", "RANK_FGM", "RANK_FGA", "RANK_FG_PCT", "RANK_FG3M", "RANK_FG3A", "RANK_FG3_PCT", "RANK_FTM", "RANK_FTA", "RANK_FT_PCT", "RANK_OREB", "RANK_DREB", "RANK_REB", "RANK_AST", "RANK_STL", "RANK_BLK", "RANK_TOV", "RANK_PTS", "RANK_EFF"], "rowSet": [[203076, "2012-13", "00", 1610612740, "NOH", "NR", "NR", "NR", 142, 89, 109, 23, 333, 309, null, 78, 77, 85, 38, 52, 44, 238, 75, 15, 159, 100, 70], [203076, "2013-14", "00", 1610612740, "NOP", "NR", "NR", "NR", 72, 24, 44, 21, 318, 322, null, 12, 11, 63, 16, 25, 19, 174, 47, 3, 119, 24, 14], [203076, "2014-15", "00", 1610612740, "NOP", "NR", "NR", "NR", 34, 4, 11, 7, 356, 338, null, 7, 9, 57, 29, 12, 15, 125, 30, 1, 139, 8, 4], [203076, "2015-16", "00", 1610612740, "NOP", "NR", "NR", "NR", 52, 14, 21, 26, 201, 185, null, 19, 18, 88, 50, 8, 14, 153, 54, 4, 64, 22, 11]], "name": "SeasonRankingsRegularSeason"}, {"headers": ["PLAYER_ID", "SEASON_ID", "LEAGUE_ID", "TEAM_ID", "TEAM_ABBREVIATION", "PLAYER_AGE", "GP", "GS", "RANK_MIN", "RANK_FGM", "RANK_FGA", "RANK_FG_PCT", "RANK_FG3M", "RANK_FG3A", "RANK_FG3_PCT", "RANK_FTM", "RANK_FTA", "RANK_FT_PCT", "RANK_OREB", "RANK_DREB", "RANK_REB", "RANK_AST", "RANK_STL", "RANK_BLK", "RANK_TOV", "RANK_PTS", "RANK_EFF"], "rowSet": [[203076, "2014-15", "00", 1610612740, "NOP", "NR", "NR", "NR", 81, 42, 54, 12, 125, 128, null, 25, 29, 14, 58, 52, 56, 102, 74, 19, 55, 42, 46]], "name": "SeasonRankingsPostSeason"}], "parameters": {"PlayerID": 203076, "LeagueID": null, "PerMode": "Totals"}}