{"resource": "playercareerstats", "resultSets": [{"headers": ["PLAYER_ID", "SEASON_ID", "LEAGUE_ID", "TEAM_ID", "TEAM_ABBREVIATION", "PLAYER_AGE", "GP", "GS", "MIN", "FGM", "FGA", "FG_PCT", "FG3M", "FG3A", "FG3_PCT", "FTM", "FTA", "FT_PCT", "OREB", "DREB", "REB", "AST", "STL", "BLK", "TOV", "PF", "PTS"], "rowSet": [[78509, "1962-63", "00", 1610612744, "SFW", 23.0, 29, null, 271, 40, 111, 0.36, null, null, null, 12, 18, 0.667, null, null, 35, 28, null, null, null, 47, 92], [78509, "1963-64", "00", 1610612755, "PHL", 24.0, 23, null, 196, 31, 105, 0.295, null, null, null, 17, 28, 0.607, null, null, 42, 12, null, null, null, 28, 79]], "name": "SeasonTotalsRegularSeason"}, {"headers": ["PLAYER_ID", "LEAGUE_ID", "TEAM_ID", "GP", "GS", "MIN", "FGM", "FGA", "FG_PCT", "FG3M", "FG3A", "FG3_PCT", "FTM", "FTA", "FT_PCT", "OREB", "DREB", "REB", "AST", "STL", "BLK", "TOV", "PF", "PTS"], "rowSet": [[78509, "00", 0, 52, null, 467, 71, 216, 0.329, null, null, null, 29, 46, 0.63, null, null, 77, 40, null, null, null, 75, 171]], "name": "CareerTotalsRegularSeason"}, {"headers": ["PLAYER_ID", "SEASON_ID", "LEAGUE_ID", "TEAM_ID", "TEAM_ABBREVIATION", "PLAYER_AGE", "GP", "GS", "MIN", "FGM", "FGA", "FG_PCT", "FG3M", "FG3A", "FG3_PCT", "FTM", "FTA", "FT_PCT", "OREB", "DREB", "REB", "AST", "STL", "BLK", "TOV", "PF", "PTS"], "rowSet": [], "name": "SeasonTotalsPostSeason"}, {"headers": ["PLAYER_ID", "LEAGUE_ID", "TEAM_ID", "GP", "GS", "MIN", "FGM", "FGA", "FG_PCT", "FG3M", "FG3A", "FG3_PCT", "FTM", "FTA", "FT_PCT", "OREB", "DREB", "REB", "AST", "STL", "BLK", "TOV", "PF", "PTS"], "rowSet": [], "name": "CareerTotalsPostSeason"}, {"headers": ["PLAYER_ID", "SEASON_ID", "LEAGUE_ID", "TEAM_ID", "TEAM_ABBREVIATION", "PLAYER_AGE", "GP", "GS", "MIN", "FGM", "FGA", "FG_PCT", "FG3M", "FG3A", "FG3_PCT", "FTM", "FTA", "FT_PCT", "OREB", "DREB", "REB", "AST", "STL", "BLK", "TOV", "PF", "PTS"], "rowSet": [], "name": "SeasonTotalsAllStarSeason"}, {"headers": ["PLAYER_ID", "LEAGUE_ID", "TEAM_ID", "GP", "GS", "MIN", "FGM", "FGA", "FG_PCT", "FG3M", "FG3A", "FG3_PCT", "FTM", "FTA", "FT_PCT", "OREB", "DREB", "REB", "AST", "STL", "BLK", "TOV", "PF", "PTS"], "rowSet": [], "name": "CareerTotalsAllStarSeason"}, {"headers": ["PLAYER_ID", "SEASON_ID", "LEAGUE_ID", "ORGANIZATION_ID", "SCHOOL_NAME", "PLAYER_AGE", "GP", "GS", "MIN", "FGM", "FGA", "FG_PCT", "FG3M", "FG3A", "FG3_PCT", "FTM", "FTA", "FT_PCT", "OREB", "DREB", "REB", "AST", "STL", "BLK", "TOV", "PF", "PTS"], "rowSet": [], "name": "SeasonTotalsCollegeSeason"}, {"headers": ["PLAYER_ID", "LEAGUE_ID", "ORGANIZATION_ID", "GP", "GS", "MIN", "FGM", "FGA", "FG_PCT", "FG3M", "FG3A", "FG3_PCT", "FTM", "FTA", "FT_PCT", "OREB", "DREB", "REB", "AST", "STL", "BLK", "TOV", "PF", "PTS"], "rowSet": [], "name": "CareerTotalsCollegeSeason"}, {"headers": ["PLAYER_ID", "SEASON_ID", "LEAGUE_ID", "TEAM_ID", "TEAM_ABBREVIATION", "PLAYER_AGE", "GP", "GS", "RANK_MIN", "RANK_FGM", "RANK_FGA", "RANK_FG_PCT", "RANK_FG3M", "RANK_FG3A", "RANK_FG3_PCT", "RANK_FTM", "RANK_FTA", "RANK_FT_PCT", "RANK_OREB", "RANK_DREB", "RANK_REB", "RANK_AST", "RANK_STL", "RANK_BLK", "RANK_TOV", "RANK_PTS", "RANK_EFF"], "rowSet": [[78509, "1962-63", "00", 1610612744, "SFW", "NR", "NR", "NR", 100, 100, 99, null, null, null, null, 102, 101, null, null, null, 103, 91, null, null, null, 100, 1], [78509, "1963-64", "00", 1610612755, "PHL", "NR", "NR", "NR", 102, 100, 98, null, null, null, null, 99, 99, null, null, null, 101, 101, null, null, null, 99, 1]], "name": "SeasonRankingsRegularSeason"}, {"headers": ["PLAYER_ID", "SEASON_ID", "LEAGUE_ID", "TEAM_ID", "TEAM_ABBREVIATION", "PLAYER_AGE", "GP", "GS", "RANK_MIN", "RANK_FGM", "RANK_FGA", "RANK_FG_PCT", "RANK_FG3M", "RANK_FG3A", "RANK_FG3_PCT", "RANK_FTM", "RANK_FTA", "RANK_FT_PCT", "RANK_OREB", "RANK_DREB", "RANK_REB", "RANK_AST", "RANK_STL", "RANK_BLK", "RANK_TOV", "RANK_PTS", "RANK_EFF"], "rowSet": [], "name": "SeasonRankingsPostSeason"}], "parameters": {"PlayerID": 78509, "LeagueID": null, "PerMode": "Totals"}}