{"resource": "playercareerstats", "resultSets": [{"headers": ["PLAYER_ID", "SEASON_ID", "LEAGUE_ID", "TEAM_ID", "TEAM_ABBREVIATION", "PLAYER_AGE", "GP", "GS", "MIN", "FGM", "FGA", "FG_PCT", "FG3M", "FG3A", "FG3_PCT", "FTM", "FTA", "FT_PCT", "OREB", "DREB", "REB", "AST", "STL", "BLK", "TOV", "PF", "PTS"], "rowSet": [[203928, "2014-15", "00", 1610612751, "BKN", 24.0, 50, 1, 531, 75, 167, 0.449, 2, 15, 0.133, 31, 54, 0.574, 47, 98, 145, 16, 10, 21, 20, 61, 183], [203928, "2015-16", "00", 1610612756, "PHX", 25.0, 6, 0, 28, 6, 12, 0.5, 0, 1, 0.0, 0, 2, 0.0, 2, 8, 10, 0, 0, 1, 0, 6, 12]], "name": "SeasonTotalsRegularSeason"}, {"headers": ["PLAYER_ID", "LEAGUE_ID", "TEAM_ID", "GP", "GS", "MIN", "FGM", "FGA", "FG_PCT", "FG3M", "FG3A", "FG3_PCT", "FTM", "FTA", "FT_PCT", "OREB", "DREB", "REB", "AST", "STL", "BLK", "TOV", "PF", "PTS"], "rowSet": [[203928, "00", 0, 56, 1, 559, 81, 179, 0.453, 2, 16, 0.125, 31, 56, 0.554, 49, 106, 155, 16, 10, 22, 20, 67, 195]], "name": "CareerTotalsRegularSeason"}, {"headers": ["PLAYER_ID", "SEASON_ID", "LEAGUE_ID", "TEAM_ID", "TEAM_ABBREVIATION", "PLAYER_AGE", "GP", "GS", "MIN", "FGM", "FGA", "FG_PCT", "FG3M", "FG3A", "FG3_PCT", "FTM", "FTA", "FT_PCT", "OREB", "DREB", "REB", "AST", "STL", "BLK", "TOV", "PF", "PTS"], "rowSet": [], "name": "SeasonTotalsPostSeason"}, {"headers": ["PLAYER_ID", "LEAGUE_ID", "TEAM_ID", "GP", "GS", "MIN", "FGM", "FGA", "FG_PCT", "FG3M", "FG3A", "FG3_PCT", "FTM", "FTA", "FT_PCT", "OREB", "DREB", "REB", "AST", "STL", "BLK", "TOV", "PF", "PTS"], "rowSet": [], "name": "CareerTotalsPostSeason"}, {"headers": ["PLAYER_ID", "SEASON_ID", "LEAGUE_ID", "TEAM_ID", "TEAM_ABBREVIATION", "PLAYER_AGE", "GP", "GS", "MIN", "FGM", "FGA", "FG_PCT", "FG3M", "FG3A", "FG3_PCT", "FTM", "FTA", "FT_PCT", "OREB", "DREB", "REB", "AST", "STL", "BLK", "TOV", "PF", "PTS"], "rowSet": [], "name": "SeasonTotalsAllStarSeason"}, {"headers": ["PLAYER_ID", "LEAGUE_ID", "TEAM_ID", "GP", "GS", "MIN", "FGM", "FGA", "FG_PCT", "FG3M", "FG3A", "FG3_PCT", "FTM", "FTA", "FT_PCT", "OREB", "DREB", "REB", "AST", "STL", "BLK", "TOV", "PF", "PTS"], "rowSet": [], "name": "CareerTotalsAllStarSeason"}, {"headers": ["PLAYER_ID", "SEASON_ID", "LEAGUE_ID", "ORGANIZATION_ID", "SCHOOL_NAME", "PLAYER_AGE", "GP", "GS", "MIN", "FGM", "FGA", "FG_PCT", "FG3M", "FG3A", "FG3_PCT", "FTM", "FTA", "FT_PCT", "OREB", "DREB", "REB", "AST", "STL", "BLK", "TOV", "PF", "PTS"], "rowSet": [[203928, "2013-14", "00", 3654, "Baylor", 23.0, 38, 38, 1103, 184, 368, 0.5, 14, 38, 0.368, 137, 214, 0.64, 107, 205, 312, 37, 15, 49, 51, 83, 519], [203928, "2012-13", "00", 3654, "Baylor", 22.0, 37, 37, 1032, 191, 313, 0.61, 3, 9, 0.333, 107, 152, 0.704, 99, 196, 295, 11, 17, 71, 30, 85, 492], [203928, "2011-12", "00", 3654, "Baylor", 21.0, 34, 1, 357, 47, 90, 0.522, 0, 2, 0.0, 27, 45, 0.6, 25, 65, 90, 3, 8, 42, 15, 45, 121], [203928, "2009-10", "00", 3654, "Baylor", 19.0, 21, 0, 97, 9, 23, 0.391, 0, 1, 0.0, 9, 13, 0.692, 12, 13, 25, 0, 2, 4, 5, 13, 27]], "name": "SeasonTotalsCollegeSeason"}, {"headers": ["PLAYER_ID", "LEAGUE_ID", "ORGANIZATION_ID", "GP", "GS", "MIN", "FGM", "FGA", "FG_PCT", "FG3M", "FG3A", "FG3_PCT", "FTM", "FTA", "FT_PCT", "OREB", "DREB", "REB", "AST", "STL", "BLK", "TOV", "PF", "PTS"], "rowSet": [[203928, "00", 0, 130, 76, 2589, 431, 794, 0.543, 17, 50, 0.34, 280, 424, 0.66, 243, 479, 722, 51, 42, 166, 101, 226, 1159]], "name": "CareerTotalsCollegeSeason"}, {"headers": ["PLAYER_ID", "SEASON_ID", "LEAGUE_ID", "TEAM_ID", "TEAM_ABBREVIATION", "PLAYER_AGE", "GP", "GS", "RANK_MIN", "RANK_FGM", "RANK_FGA", "RANK_FG_PCT", "RANK_FG3M", "RANK_FG3A", "RANK_FG3_PCT", "RANK_FTM", "RANK_FTA", "RANK_FT_PCT", "RANK_OREB", "RANK_DREB", "RANK_REB", "RANK_AST", "RANK_STL", "RANK_BLK", "RANK_TOV", "RANK_PTS", "RANK_EFF"], "rowSet": [[203928, "2014-15", "00", 1610612751, "BKN", "NR", "NR", "NR", 359, 343, 349, null, 343, 330, null, 320, 298, null, 195, 302, 283, 390, 379, 163, 376, 352, 341], [203928, "2015-16", "00", 1610612756, "PHX", "NR", "NR", "NR", 421, 405, 409, null, 340, 356, null, 419, 409, null, 391, 400, 404, 430, 423, 366, 430, 410, 408]], "name": "SeasonRankingsRegularSeason"}, {"headers": ["PLAYER_ID", "SEASON_ID", "LEAGUE_ID", "TEAM_ID", "TEAM_ABBREVIATION", "PLAYER_AGE", "GP", "GS", "RANK_MIN", "RANK_FGM", "RANK_FGA", "RANK_FG_PCT", "RANK_FG3M", "RANK_FG3A", "RANK_FG3_PCT", "RANK_FTM", "RANK_FTA", "RANK_FT_PCT", "RANK_OREB", "RANK_DREB", "RANK_REB", "RANK_AST", "RANK_STL", "RANK_BLK", "RANK_TOV", "RANK_PTS", "RANK_EFF"], "rowSet": [], "name": "SeasonRankingsPostSeason"}], "parameters": {"PlayerID": 203928, "LeagueID": null, "PerMode": "Totals"}}