{"resource": "playercareerstats", "resultSets": [{"headers": ["PLAYER_ID", "SEASON_ID", "LEAGUE_ID", "TEAM_ID", "TEAM_ABBREVIATION", "PLAYER_AGE", "GP", "GS", "MIN", "FGM", "FGA", "FG_PCT", "FG3M", "FG3A", "FG3_PCT", "FTM", "FTA", "FT_PCT", "OREB", "DREB", "REB", "AST", "STL", "BLK", "TOV", "PF", "PTS"], "rowSet": [[77969, "1988-89", "00", 1610612738, "BOS", 23.0, 28, 0, 91, 12, 31, 0.387, 0, 1, 0.0, 16, 25, 0.64, 9, 15, 24, 3, 4, 1, 9, 21, 40]], "name": "SeasonTotalsRegularSeason"}, {"headers": ["PLAYER_ID", "LEAGUE_ID", "TEAM_ID", "GP", "GS", "MIN", "FGM", "FGA", "FG_PCT", "FG3M", "FG3A", "FG3_PCT", "FTM", "FTA", "FT_PCT", "OREB", "DREB", "REB", "AST", "STL", "BLK", "TOV", "PF", "PTS"], "rowSet": [[77969, "00", 0, 28, 0, 91, 12, 31, 0.387, 0, 1, 0.0, 16, 25, 0.64, 9, 15, 24, 3, 4, 1, 9, 21, 40]], "name": "CareerTotalsRegularSeason"}, {"headers": ["PLAYER_ID", "SEASON_ID", "LEAGUE_ID", "TEAM_ID", "TEAM_ABBREVIATION", "PLAYER_AGE", "GP", "GS", "MIN", "FGM", "FGA", "FG_PCT", "FG3M", "FG3A", "FG3_PCT", "FTM", "FTA", "FT_PCT", "OREB", "DREB", "REB", "AST", "STL", "BLK", "TOV", "PF", "PTS"], "rowSet": [], "name": "SeasonTotalsPostSeason"}, {"headers": ["PLAYER_ID", "LEAGUE_ID", "TEAM_ID", "GP", "GS", "MIN", "FGM", "FGA", "FG_PCT", "FG3M", "FG3A", "FG3_PCT", "FTM", "FTA", "FT_PCT", "OREB", "DREB", "REB", "AST", "STL", "BLK", "TOV", "PF", "PTS"], "rowSet": [], "name": "CareerTotalsPostSeason"}, {"headers": ["PLAYER_ID", "SEASON_ID", "LEAGUE_ID", "TEAM_ID", "TEAM_ABBREVIATION", "PLAYER_AGE", "GP", "GS", "MIN", "FGM", "FGA", "FG_PCT", "FG3M", "FG3A", "FG3_PCT", "FTM", "FTA", "FT_PCT", "OREB", "DREB", "REB", "AST", "STL", "BLK", "TOV", "PF", "PTS"], "rowSet": [], "name": "SeasonTotalsAllStarSeason"}, {"headers": ["PLAYER_ID", "LEAGUE_ID", "TEAM_ID", "GP", "GS", "MIN", "FGM", "FGA", "FG_PCT", "FG3M", "FG3A", "FG3_PCT", "FTM", "FTA", "FT_PCT", "OREB", "DREB", "REB", "AST", "STL", "BLK", "TOV", "PF", "PTS"], "rowSet": [], "name": "CareerTotalsAllStarSeason"}, {"headers": ["PLAYER_ID", "SEASON_ID", "LEAGUE_ID", "ORGANIZATION_ID", "SCHOOL_NAME", "PLAYER_AGE", "GP", "GS", "MIN", "FGM", "FGA", "FG_PCT", "FG3M", "FG3A", "FG3_PCT", "FTM", "FTA", "FT_PCT", "OREB", "DREB", "REB", "AST", "STL", "BLK", "TOV", "PF", "PTS"], "rowSet": [], "name": "SeasonTotalsCollegeSeason"}, {"headers": ["PLAYER_ID", "LEAGUE_ID", "ORGANIZATION_ID", "GP", "GS", "MIN", "FGM", "FGA", "FG_PCT", "FG3M", "FG3A", "FG3_PCT", "FTM", "FTA", "FT_PCT", "OREB", "DREB", "REB", "AST", "STL", "BLK", "TOV", "PF", "PTS"], "rowSet": [], "name": "CareerTotalsCollegeSeason"}, {"headers": ["PLAYER_ID", "SEASON_ID", "LEAGUE_ID", "TEAM_ID", "TEAM_ABBREVIATION", "PLAYER_AGE", "GP", "GS", "RANK_MIN", "RANK_FGM", "RANK_FGA", "RANK_FG_PCT", "RANK_FG3M", "RANK_FG3A", "RANK_FG3_PCT", "RANK_FTM", "RANK_FTA", "RANK_FT_PCT", "RANK_OREB", "RANK_DREB", "RANK_REB", "RANK_AST", "RANK_STL", "RANK_BLK", "RANK_TOV", "RANK_PTS", "RANK_EFF"], "rowSet": [[77969, "1988-89", "00", 1610612738, "BOS", "NR", "NR", "NR", 326, 322, 325, null, 209, 262, null, 298, 293, null, 307, 314, 315, 327, 316, 305, 318, 316, 322]], "name": "SeasonRankingsRegularSeason"}, {"headers": ["PLAYER_ID", "SEASON_ID", "LEAGUE_ID", "TEAM_ID", "TEAM_ABBREVIATION", "PLAYER_AGE", "GP", "GS", "RANK_MIN", "RANK_FGM", "RANK_FGA", "RANK_FG_PCT", "RANK_FG3M", "RANK_FG3A", "RANK_FG3_PCT", "RANK_FTM", "RANK_FTA", "RANK_FT_PCT", "RANK_OREB", "RANK_DREB", "RANK_REB", "RANK_AST", "RANK_STL", "RANK_BLK", "RANK_TOV", "RANK_PTS", "RANK_EFF"], "rowSet": [], "name": "SeasonRankingsPostSeason"}], "parameters": {"PlayerID": 77969, "LeagueID": null, "PerMode": "Totals"}}